pulse/__init__.py
pulse/_examples.py
pulse/app.py
pulse/channel.py
pulse/cli/__init__.py
pulse/cli/cmd.py
pulse/cli/dependencies.py
pulse/cli/folder_lock.py
pulse/cli/helpers.py
pulse/cli/logging.py
pulse/cli/models.py
pulse/cli/packages.py
pulse/cli/processes.py
pulse/cli/secrets.py
pulse/cli/uvicorn_log_config.py
pulse/code_analysis.py
pulse/codegen/__init__.py
pulse/codegen/codegen.py
pulse/codegen/templates/__init__.py
pulse/codegen/templates/layout.py
pulse/codegen/templates/route.py
pulse/codegen/templates/routes_ts.py
pulse/codegen/utils.py
pulse/component.py
pulse/components/__init__.py
pulse/components/for_.py
pulse/components/if_.py
pulse/components/react_router.py
pulse/context.py
pulse/cookies.py
pulse/debounce.py
pulse/decorators.py
pulse/dom/__init__.py
pulse/dom/elements.py
pulse/dom/events.py
pulse/dom/props.py
pulse/dom/svg.py
pulse/dom/tags.py
pulse/dom/tags.pyi
pulse/env.py
pulse/forms.py
pulse/helpers.py
pulse/hooks/__init__.py
pulse/hooks/core.py
pulse/hooks/effects.py
pulse/hooks/init.py
pulse/hooks/runtime.py
pulse/hooks/setup.py
pulse/hooks/stable.py
pulse/hooks/state.py
pulse/js/__init__.py
pulse/js/__init__.pyi
pulse/js/_types.py
pulse/js/abort_controller.py
pulse/js/array.py
pulse/js/array_buffer.py
pulse/js/blob.py
pulse/js/console.py
pulse/js/crypto.py
pulse/js/custom_event.py
pulse/js/date.py
pulse/js/document.py
pulse/js/dom_parser.py
pulse/js/error.py
pulse/js/fetch_api.py
pulse/js/file.py
pulse/js/file_reader.py
pulse/js/form_data.py
pulse/js/intersection_observer.py
pulse/js/intl.py
pulse/js/json.py
pulse/js/map.py
pulse/js/math.py
pulse/js/mutation_observer.py
pulse/js/navigator.py
pulse/js/number.py
pulse/js/obj.py
pulse/js/object.py
pulse/js/performance_observer.py
pulse/js/promise.py
pulse/js/pulse.py
pulse/js/react.py
pulse/js/regexp.py
pulse/js/resize_observer.py
pulse/js/set.py
pulse/js/string.py
pulse/js/text_encoding.py
pulse/js/url.py
pulse/js/weakmap.py
pulse/js/weakset.py
pulse/js/window.py
pulse/messages.py
pulse_framework-0.1.76.dist-info/WHEEL
pulse_framework-0.1.76.dist-info/entry_points.txt
pulse_framework-0.1.76.dist-info/METADATA
pulse_framework-0.1.76.dist-info/RECORD
