Metadata-Version: 2.3
Name: pulse-framework
Version: 0.1.76
Summary: Pulse - Full-stack framework for building real-time React applications in Python
Requires-Dist: fastapi>=0.128.0
Requires-Dist: uvicorn>=0.24.0
Requires-Dist: mako>=1.3.10
Requires-Dist: typer>=0.16.0
Requires-Dist: python-socketio>=5.16.0
Requires-Dist: rich>=13.7.1
Requires-Dist: python-multipart>=0.0.22
Requires-Dist: python-dateutil>=2.9.0.post0
Requires-Dist: starlette>=0.50.0,<0.51.0
Requires-Dist: urllib3>=2.6.3
Requires-Dist: watchfiles>=1.1.0
Requires-Dist: httpx>=0.28.1
Requires-Dist: aiohttp>=3.12.0
Requires-Python: >=3.12
